LICENSE
MANIFEST.in
README.md
setup.cfg
setup.py
category/__init__.py
category/admin.py
category/apps.py
category/models.py
category/tests.py
category/views.py
category/locale/en/LC_MESSAGES/django.mo
category/locale/en/LC_MESSAGES/django.po
category/locale/zh_hans/LC_MESSAGES/django.mo
category/locale/zh_hans/LC_MESSAGES/django.po
category/migrations/__init__.py
django_simple_category.egg-info/PKG-INFO
django_simple_category.egg-info/SOURCES.txt
django_simple_category.egg-info/dependency_links.txt
django_simple_category.egg-info/requires.txt
django_simple_category.egg-info/top_level.txt