Metadata-Version: 2.1
Name: django-simple-category
Version: 1.0.0
Summary: A simple and extendable hierarchical category app for django.
Home-page: https://www.github.com/xionxiao/django-simple-category/
Author: Allen Shaw
Author-email: xhui.xiao@gmail.com
License: BSD-3-Clause
Platform: UNKNOWN
Classifier: Environment :: Web Environment
Classifier: Framework :: Django
Classifier: Intended Audience :: Developers
Classifier: License :: OSI Approved :: BSD License
Classifier: Operating System :: OS Independent
Classifier: Programming Language :: Python
Classifier: Topic :: Internet :: WWW/HTTP
Classifier: Topic :: Internet :: WWW/HTTP :: Dynamic Content
